vastweb/__init__.py
vastweb/vastweb.py
vastweb-0.2.0.dist-info/METADATA
vastweb-0.2.0.dist-info/WHEEL
vastweb-0.2.0.dist-info/top_level.txt
vastweb-0.2.0.dist-info/RECORD
