Metadata-Version: 2.1
Name: vastweb
Version: 0.2.0
Summary: A module for simplifying web development with Flask.
Home-page: https://github.com/your_username/vastweb
Author: Your Name
Author-email: your.email@example.com
License: MIT
Classifier: Programming Language :: Python :: 3
Classifier: License :: OSI Approved :: MIT License
Classifier: Operating System :: OS Independent
Requires-Dist: Flask
